keyinfostruct/__init__.py
keyinfostruct/main.py
keyinfostruct/prompts.py
keyinfostruct-2025.12.22082410.dist-info/METADATA
keyinfostruct-2025.12.22082410.dist-info/WHEEL
keyinfostruct-2025.12.22082410.dist-info/top_level.txt
keyinfostruct-2025.12.22082410.dist-info/RECORD
