Metadata-Version: 2.4
Name: keyinfostruct
Version: 2025.12.22082410
Summary: keyinfostruct extracts and structures key info from personal texts, highlighting main points, emotions, and suggested actions for better organization.
Author-email: keyinfostruct <hi@eugene.plus>
License: MIT
Project-URL: Homepage, https://github.com/chigwell/keyinfostruct
Requires-Python: >=3.9
Requires-Dist: langchain-llm7>=0.0.0
Requires-Dist: llmatch-messages>=0.0.0
Requires-Dist: langchain-core>=0.3.0
